tw_md/__init__.py
tw_md/cli.py
tw_md/domain/commit.py
tw_md/domain/repository.py
tw_md/errors/github_errors.py
tw_md/service/github_service.py
tw_md/service/markdown_service.py
tw_md-0.2.2.dist-info/entry_points.txt
tw_md-0.2.2.dist-info/WHEEL
tw_md-0.2.2.dist-info/METADATA
tw_md-0.2.2.dist-info/RECORD
