Metadata-Version: 2.1
Name: tw-md
Version: 0.2.2
Summary: 
Author: Cleyson Lima
Author-email: cleysonph@gmail.com
Requires-Python: >=3.8,<4.0
Classifier: Programming Language :: Python :: 3
Classifier: Programming Language :: Python :: 3.10
Classifier: Programming Language :: Python :: 3.8
Classifier: Programming Language :: Python :: 3.9
Requires-Dist: click (>=8.1.3,<9.0.0)
Requires-Dist: requests (>=2.27.1,<3.0.0)
